cxplain/__init__.py
cxplain/base_explainer.py
cxplain/errors.py
cxplain/gradient.py
cxplain/metrics.py
cxplain/neon.py
cxplain/shap.py
cxplain/tree.py
cxplain/util.py
cxplain/version.py
cxplain/xkm.py
clusterxplain-0.1.0.dist-info/LICENSE
clusterxplain-0.1.0.dist-info/METADATA
clusterxplain-0.1.0.dist-info/WHEEL
clusterxplain-0.1.0.dist-info/RECORD
