Metadata-Version: 2.1
Name: clusterxplain
Version: 0.1.0
Summary: Provide feature relevance scores fo clustering.
Home-page: https://github.com/AlexF1994/cluster-explain
License: MIT
Author: Alexander Fottner
Author-email: alexander.fottner@uni-a.de
Requires-Python: >=3.8,<4.0
Classifier: License :: OSI Approved :: MIT License
Classifier: Programming Language :: Python :: 3
Classifier: Programming Language :: Python :: 3.8
Classifier: Programming Language :: Python :: 3.9
Classifier: Programming Language :: Python :: 3.10
Classifier: Programming Language :: Python :: 3.11
Requires-Dist: ExKMC (>=0.0.3,<0.0.4)
Requires-Dist: importlib-metadata (>=1.0,<2.0) ; python_version < "3.8"
Requires-Dist: matplotlib (>=3.6.0,<4.0.0)
Requires-Dist: nptyping (>=2.3.1,<3.0.0)
Requires-Dist: pandas (>=1.5.0,<2.0.0)
Requires-Dist: pyhocon (>=0.3.54,<0.4.0)
Requires-Dist: scikit-learn (>=1.1.2,<2.0.0)
Requires-Dist: seaborn (>=0.12.2,<0.13.0)
Requires-Dist: shap (>=0.41.0,<0.42.0)
Project-URL: Changelog, https://github.com/me/spam/blob/master/CHANGELOG.md
Project-URL: Documentation, https://readthedocs.org/projects/cluster-explain/
Project-URL: Repository, https://github.com/AlexF1994/cluster-explain
